pyaoc/README.jinja2
pyaoc/day_benchmark.py
pyaoc/day_creation.py
pyaoc/day_launch.py
pyaoc/day_subject.py
pyaoc/day_year.py
pyaoc/part.jinja2
pyaoc/pyaoc.py
pyaoc/readme_generation.py
pyaoc-0.0.1.dist-info/LICENSE
pyaoc-0.0.1.dist-info/METADATA
pyaoc-0.0.1.dist-info/WHEEL
pyaoc-0.0.1.dist-info/entry_points.txt
pyaoc-0.0.1.dist-info/top_level.txt
pyaoc-0.0.1.dist-info/RECORD
