Metadata-Version: 2.1
Name: pyaoc
Version: 0.0.1
Summary: Python Advent of Code package
Author: Aurélien TRONCY
License: Mozilla Public License Version 2.0
Project-URL: Homepage, https://github.com/Nounoursdestavernes/PyAOC
Project-URL: Repository, https://github.com/Nounoursdestavernes/PyAOC.git
Keywords: adventofcode,aoc,advent of code
Classifier: Development Status :: 1 - Planning
Classifier: Intended Audience :: Developers
Classifier: License :: OSI Approved :: Mozilla Public License 2.0 (MPL 2.0)
Classifier: Programming Language :: Python
Classifier: Operating System :: Unix
Requires-Python: >=3.9
License-File: LICENSE
Requires-Dist: Jinja2 >=3.1.2
Requires-Dist: requests >=2.31.0
